lyzr_automata/__init__.py
lyzr_automata/data_models.py
lyzr_automata/logger.py
lyzr_automata/agents/__init__.py
lyzr_automata/agents/agent_base.py
lyzr_automata/ai_models/__init__.py
lyzr_automata/ai_models/model_base.py
lyzr_automata/ai_models/openai.py
lyzr_automata/ai_models/perplexity.py
lyzr_automata/examples/__init__.py
lyzr_automata/examples/linkedin_post_automation.py
lyzr_automata/memory/__init__.py
lyzr_automata/memory/llama_index.py
lyzr_automata/memory/memory_literals.py
lyzr_automata/memory/open_ai.py
lyzr_automata/pipelines/__init__.py
lyzr_automata/pipelines/linear_sync_pipeline.py
lyzr_automata/tasks/__init__.py
lyzr_automata/tasks/task_base.py
lyzr_automata/tasks/task_literals.py
lyzr_automata/tasks/util_tasks.py
lyzr_automata/tools/__init__.py
lyzr_automata/tools/devto.py
lyzr_automata/tools/email.py
lyzr_automata/tools/linkedin.py
lyzr_automata/tools/llama_tool.py
lyzr_automata/tools/prebuilt_tools.py
lyzr_automata/tools/tool_base.py
lyzr_automata/utils/__init__.py
lyzr_automata/utils/prompt_utils.py
lyzr_automata/utils/resource_handler.py
lyzr_automata-0.1.3.dist-info/METADATA
lyzr_automata-0.1.3.dist-info/WHEEL
lyzr_automata-0.1.3.dist-info/top_level.txt
lyzr_automata-0.1.3.dist-info/RECORD
