Metadata-Version: 2.1
Name: lyzr-automata
Version: 0.1.3
Summary: low-code multi-agent automation framework
Home-page: https://github.com/lyzrcore/lyzr-automata
Author: lyzr
License: MIT
Platform: UNKNOWN
Classifier: License :: OSI Approved :: MIT License
Classifier: Operating System :: OS Independent
Requires-Python: >=3.8.1, <3.12
Requires-Dist: openai ==1.3.4
Requires-Dist: requests ==2.31.0
